README.md
setup.py
kylileo/__init__.py
kylileo.egg-info/PKG-INFO
kylileo.egg-info/SOURCES.txt
kylileo.egg-info/dependency_links.txt
kylileo.egg-info/top_level.txt