Metadata-Version: 1.0
Name: kylileo
Version: 0.1
Summary: A python package test
Home-page: https://github.com/kyllebirnie/kylileo
Author: Kylle
Author-email: kyllebirnie@googlemail.com
License: MIT
Platform: UNKNOWN
